MANIFEST.in
README.rst
setup.py
ckanext/__init__.py
ckanext/zh_search/__init__.py
ckanext/zh_search/plugin.py
ckanext/zh_search/aaa/__init__.py
ckanext/zh_search/tests/__init__.py
ckanext/zh_search/tests/test_plugin.py
ckanext_zh_search.egg-info/PKG-INFO
ckanext_zh_search.egg-info/SOURCES.txt
ckanext_zh_search.egg-info/dependency_links.txt
ckanext_zh_search.egg-info/entry_points.txt
ckanext_zh_search.egg-info/requires.txt
ckanext_zh_search.egg-info/top_level.txt