Metadata-Version: 1.1
Name: ckanext-zh-search
Version: 0.0.2
Summary: fix search for chinese.
Home-page: https://github.com//ckanext-zh_search
Author: nispc
Author-email: nispc@nispc.tw
License: AGPL
Keywords: CKAN
Platform: UNKNOWN
Classifier: Development Status :: 4 - Beta
Classifier: License :: OSI Approved :: GNU Affero General Public License v3 or later (AGPLv3+)
Classifier: Programming Language :: Python :: 2.6
Classifier: Programming Language :: Python :: 2.7
